CONTRIBUTORS.txt
LICENSE.txt
MANIFEST.in
README.rst
setup.py
django_profiletools.egg-info/PKG-INFO
django_profiletools.egg-info/SOURCES.txt
django_profiletools.egg-info/dependency_links.txt
django_profiletools.egg-info/not-zip-safe
django_profiletools.egg-info/requires.txt
django_profiletools.egg-info/top_level.txt
docs/Makefile
docs/conf.py
docs/index.rst
docs/make.bat
docs/proBlue/LICENSE.txt
docs/proBlue/README.txt
docs/proBlue/theme.conf
docs/proBlue/static/proBlue.css
profiletools/__init__.py
profiletools/context_processors.py
profiletools/forms.py
profiletools/middleware.py
profiletools/models.py
profiletools/utils.py
profiletools/views.py