Metadata-Version: 1.1
Name: django-profiletools
Version: 0.2.1
Summary: Tools for Profile models in Django.
Home-page: http://github.com/pydanny/django-profiletools
Author: Daniel Greenfeld
Author-email: pydanny@gmail.com
License: MIT
Keywords: django,profiles
Platform: UNKNOWN
Classifier: Development Status :: 4 - Beta
Classifier: Environment :: Web Environment
Classifier: Framework :: Django
Classifier: License :: OSI Approved :: BSD License
Classifier: Operating System :: OS Independent
Classifier: Programming Language :: Python :: 2.7
Classifier: Topic :: Internet :: WWW/HTTP
Classifier: Topic :: Internet :: WWW/HTTP :: Dynamic Content
Classifier: Topic :: Software Development :: Libraries :: Python Modules
